jsondataferret/__init__.py
jsondataferret/admin.py
jsondataferret/apps.py
jsondataferret/filters.py
jsondataferret/forms.py
jsondataferret/models.py
jsondataferret/urls.py
jsondataferret/utils.py
jsondataferret/views.py
jsondataferret/management/__init__.py
jsondataferret/management/commands/__init__.py
jsondataferret/management/commands/purgerecord.py
jsondataferret/management/commands/runeventstreamtodatabase.py
jsondataferret/management/commands/updatejsonschemavalidations.py
jsondataferret/migrations/0001_initial.py
jsondataferret/migrations/0002_jsondataferret.py
jsondataferret/migrations/0003_auto_20220526_0923.py
jsondataferret/migrations/0004_auto_20220603_0827.py
jsondataferret/migrations/__init__.py
jsondataferret/pythonapi/__init__.py
jsondataferret/pythonapi/newevent.py
jsondataferret/pythonapi/purge.py
jsondataferret/pythonapi/runevents.py
jsondataferret/templates/jsondataferret/base.html
jsondataferret/templates/jsondataferret/events.html
jsondataferret/templates/jsondataferret/index.html
jsondataferret/templates/jsondataferret/types.html
jsondataferret/templates/jsondataferret/common/pagination.html
jsondataferret/templates/jsondataferret/edit/index.html
jsondataferret/templates/jsondataferret/edit/index_table_contents.html
jsondataferret/templates/jsondataferret/event/index.html
jsondataferret/templates/jsondataferret/type/index.html
jsondataferret/templates/jsondataferret/type/records.html
jsondataferret/templates/jsondataferret/type/records_needing_moderation.html
jsondataferret/templates/jsondataferret/type/record/edit_json_schema.html
jsondataferret/templates/jsondataferret/type/record/events.html
jsondataferret/templates/jsondataferret/type/record/import_form.html
jsondataferret/templates/jsondataferret/type/record/index.html
jsondataferret/templates/jsondataferret/type/record/moderate.html
jsondataferret/tests/__init__.py
jsondataferret/tests/test_get_field_list_from_json.py
jsondataferret/tests/test_model_cachedrecordhistory.py
jsondataferret-0.7.1.dist-info/LICENSE
jsondataferret-0.7.1.dist-info/METADATA
jsondataferret-0.7.1.dist-info/WHEEL
jsondataferret-0.7.1.dist-info/top_level.txt
jsondataferret-0.7.1.dist-info/RECORD
